rtvamp/__init__.py
rtvamp/_bindings.cp38-win32.pyd
rtvamp/example-plugin.dll
rtvamp/example-plugin.lib
rtvamp-0.3.1.dist-info/LICENSE
rtvamp-0.3.1.dist-info/METADATA
rtvamp-0.3.1.dist-info/WHEEL
rtvamp-0.3.1.dist-info/top_level.txt
rtvamp-0.3.1.dist-info/RECORD
