Metadata-Version: 2.1
Name: rtvamp
Version: 0.3.1
Summary: Vamp plugin host for real-time audio feature analysis
Home-page: https://github.com/lukasberbuer/rt-vamp-plugin-sdk
Author: Lukas Berbuer
Author-email: lukas.berbuer@gmail.com
License: MIT
Keywords: Vamp,plugin,audio,sound,music,analysis,feature extraction,real-time
Classifier: Development Status :: 4 - Beta
Classifier: Intended Audience :: Developers
Classifier: Intended Audience :: Science/Research
Classifier: Topic :: Scientific/Engineering
Classifier: Topic :: Multimedia :: Sound/Audio
Classifier: Topic :: Multimedia :: Sound/Audio :: Analysis
Classifier: License :: OSI Approved :: MIT License
Classifier: Programming Language :: Python :: 3
Classifier: Programming Language :: Python :: 3.6
Classifier: Programming Language :: Python :: 3.7
Classifier: Programming Language :: Python :: 3.8
Classifier: Programming Language :: Python :: 3.9
Classifier: Programming Language :: Python :: 3.10
Classifier: Programming Language :: Python :: 3.11
Classifier: Programming Language :: Python :: 3.12
Classifier: Operating System :: OS Independent
Requires-Python: >=3.6
License-File: LICENSE
Requires-Dist: numpy
Requires-Dist: dataclasses >=0.6 ; python_version < "3.7"
Provides-Extra: dev
Requires-Dist: sphinx >=5 ; extra == 'dev'
Requires-Dist: sphinx-gallery ; extra == 'dev'
Requires-Dist: myst-parser ; extra == 'dev'
Requires-Dist: furo ; extra == 'dev'
Requires-Dist: librosa ; extra == 'dev'
Requires-Dist: matplotlib ; extra == 'dev'
Requires-Dist: pytest >=6 ; extra == 'dev'
Requires-Dist: black ; extra == 'dev'
Requires-Dist: isort ; extra == 'dev'
Requires-Dist: mypy >=0.9 ; extra == 'dev'
Requires-Dist: pylint >=2.5 ; extra == 'dev'
Requires-Dist: tox >=3.4 ; extra == 'dev'
Provides-Extra: docs
Requires-Dist: sphinx >=5 ; extra == 'docs'
Requires-Dist: sphinx-gallery ; extra == 'docs'
Requires-Dist: myst-parser ; extra == 'docs'
Requires-Dist: furo ; extra == 'docs'
Requires-Dist: librosa ; extra == 'docs'
Requires-Dist: matplotlib ; extra == 'docs'
Provides-Extra: tests
Requires-Dist: pytest >=6 ; extra == 'tests'
Provides-Extra: tools
Requires-Dist: black ; extra == 'tools'
Requires-Dist: isort ; extra == 'tools'
Requires-Dist: mypy >=0.9 ; extra == 'tools'
Requires-Dist: pylint >=2.5 ; extra == 'tools'
Requires-Dist: tox >=3.4 ; extra == 'tools'
